MANIFEST.in
README.md
pyproject.toml
requirements.txt
setup.cfg
setup.py
t_page_object/__init__.py
t_page_object/bot_config.py
t_page_object/bug_catcher_meta.py
t_page_object/decorators.py
t_page_object/exceptions.py
t_page_object/selenium_manager.py
t_page_object.egg-info/PKG-INFO
t_page_object.egg-info/SOURCES.txt
t_page_object.egg-info/dependency_links.txt
t_page_object.egg-info/not-zip-safe
t_page_object.egg-info/requires.txt
t_page_object.egg-info/top_level.txt
t_page_object/base/__init__.py
t_page_object/base/base_app.py
t_page_object/base/base_page.py
t_page_object/base/endpoint_element.py
t_page_object/base/ui_element.py
t_page_object/elements/__init__.py
t_page_object/elements/button_element.py
t_page_object/elements/checkbox_element.py
t_page_object/elements/container_element.py
t_page_object/elements/dropdown_element.py
t_page_object/elements/iframe_element.py
t_page_object/elements/image_element.py
t_page_object/elements/input_element.py
t_page_object/elements/sentinel_element.py
t_page_object/elements/table_element.py
t_page_object/elements/table_row_element.py
t_page_object/elements/text_element.py
tests/test_decorators.py
tests/test_dropdown_element.py
tests/test_methods_chrome.py
tests/test_methods_endpoints.py
tests/test_methods_firefox.py
tests/test_sentinel.py
tests/test_t_page_object_imports.py
tests/test_ui_element_quote_handling.py