Metadata-Version: 2.4
Name: t_page_object
Version: 1.1.6
Summary: Cookiecutter template for Thoughtful pip package
Home-page: https://www.thoughtful.ai/
Author: Thoughtful
Author-email: support@thoughtful.ai
Keywords: t_page_object
Classifier: Intended Audience :: Developers
Classifier: Natural Language :: English
Classifier: Programming Language :: Python :: 3
Classifier: Programming Language :: Python :: 3.9
Requires-Python: >=3.9
Requires-Dist: datetime==5.5
Requires-Dist: t_bug_catcher==0.6.14
Requires-Dist: rpaframework==31.0.0
Requires-Dist: t_object==0.1.8
Requires-Dist: types-selenium==3.141.9
Requires-Dist: types-retry==0.9.9.4
Requires-Dist: types-setuptools==75.2.0.20241025
Dynamic: author
Dynamic: author-email
Dynamic: classifier
Dynamic: description
Dynamic: description-content-type
Dynamic: home-page
Dynamic: keywords
Dynamic: requires-dist
Dynamic: requires-python
Dynamic: summary
